MANIFEST.in
README.md
setup.py
jsonobject/__init__.py
jsonobject/api.py
jsonobject/base.py
jsonobject/base_properties.py
jsonobject/containers.py
jsonobject/exceptions.py
jsonobject/properties.py
jsonobject/utils.py
paymill_jsonobject.egg-info/PKG-INFO
paymill_jsonobject.egg-info/SOURCES.txt
paymill_jsonobject.egg-info/dependency_links.txt
paymill_jsonobject.egg-info/requires.txt
paymill_jsonobject.egg-info/top_level.txt
test/test_couchdbkit.py
test/test_stringconversions.py
test/tests.py