Metadata-Version: 1.0
Name: paymill-jsonobject
Version: 0.7.0beta
Summary: This is a fork of jsonobject library and is only intended to be used temporary until jsonobject 0.7.0 release is out.
Home-page: https://github.com/dannyroberts/jsonobject
Author: Aleksandar Yalnazov
Author-email: aleksandar.yalnazov@paymill.de
License: UNKNOWN
Platform: UNKNOWN
